parallel_developer/__init__.py
parallel_developer/cli.py
parallel_developer/orchestrator.py
parallel_developer/controller/__init__.py
parallel_developer/controller/commands.py
parallel_developer/controller/events.py
parallel_developer/controller/flow.py
parallel_developer/controller/history.py
parallel_developer/controller/pause.py
parallel_developer/controller/workflow_runner.py
parallel_developer/services/__init__.py
parallel_developer/services/codex_monitor.py
parallel_developer/services/log_manager.py
parallel_developer/services/tmux_manager.py
parallel_developer/services/worktree_manager.py
parallel_developer/stores/__init__.py
parallel_developer/stores/session_manifest.py
parallel_developer/stores/settings_store.py
parallel_developer/ui/widgets.py
pdev-0.1.2.dist-info/METADATA
pdev-0.1.2.dist-info/WHEEL
pdev-0.1.2.dist-info/entry_points.txt
pdev-0.1.2.dist-info/RECORD
