Metadata-Version: 2.4
Name: pdev
Version: 0.1.2
Summary: CLI orchestrator for parallel Codex agents with tmux and git worktree integration.
Author: Parallel Developer Team
Requires-Python: >=3.11
Requires-Dist: gitpython>=3.1.45
Requires-Dist: libtmux>=0.46.2
Requires-Dist: platformdirs>=4.3.6
Requires-Dist: pydantic>=2.9
Requires-Dist: pyyaml>=6.0.2
Requires-Dist: rich>=13.9.2
Requires-Dist: textual>=0.51.1
Requires-Dist: typer>=0.12.3
Requires-Dist: watchfiles>=0.23.0
